pflacs/__init__.py
pflacs/pflacs.py
pflacs-0.2.0.dist-info/LICENSE
pflacs-0.2.0.dist-info/METADATA
pflacs-0.2.0.dist-info/WHEEL
pflacs-0.2.0.dist-info/top_level.txt
pflacs-0.2.0.dist-info/RECORD
