Metadata-Version: 2.1
Name: pflacs
Version: 0.2.0
Summary: Faster load-cases and parameter studies.
Home-page: https://github.com/qwilka/pflacs
Author: Stephen McEntee
Author-email: stephenmce@gmail.com
License: UNKNOWN
Keywords: science engineering computational productivity
Platform: UNKNOWN
Classifier: Development Status :: 3 - Alpha
Classifier: License :: OSI Approved :: MIT License
Classifier: Programming Language :: Python :: 3.6
Classifier: Topic :: Scientific/Engineering
Classifier: Intended Audience :: Science/Research
Classifier: Natural Language :: English
Requires-Python: >=3.6
Requires-Dist: vntree
Requires-Dist: numpy
Requires-Dist: pandas
Requires-Dist: tables
